pyseen/__init__.py
pyseen/core.py
pyseen-0.1.0.dist-info/METADATA
pyseen-0.1.0.dist-info/WHEEL
pyseen-0.1.0.dist-info/top_level.txt
pyseen-0.1.0.dist-info/RECORD
